fancycompleter.py
fancycompleter-0.9.0.dist-info/METADATA
fancycompleter-0.9.0.dist-info/WHEEL
fancycompleter-0.9.0.dist-info/top_level.txt
fancycompleter-0.9.0.dist-info/RECORD
