Metadata-Version: 2.1
Name: fancycompleter
Version: 0.9.0
Summary: colorful TAB completion for Python prompt
Home-page: https://github.com/pdbpp/fancycompleter
Author: Antonio Cuni
Author-email: anto.cuni@gmail.com
Maintainer: Daniel Hahler
License: BSD
Keywords: rlcompleter prompt tab color completion
Platform: UNKNOWN
Classifier: Development Status :: 4 - Beta
Classifier: Environment :: Console
Classifier: Intended Audience :: Developers
Classifier: License :: OSI Approved :: BSD License
Classifier: Operating System :: Microsoft :: Windows
Classifier: Operating System :: POSIX
Classifier: Programming Language :: Python :: 2.6
Classifier: Programming Language :: Python :: 2.7
Classifier: Programming Language :: Python :: 3.5
Classifier: Programming Language :: Python :: 3.6
Classifier: Programming Language :: Python :: 3.7
Classifier: Programming Language :: Python :: 3.8
Classifier: Topic :: Utilities
Requires-Dist: pyrepl (>=0.8.2)
Requires-Dist: pyreadline ; platform_system == "Windows"
